{
  "rows": 12,
  "cols": [
    "ano",
    "entidade",
    "empenhado",
    "liquidado",
    "pago"
  ],
  "sample": [
    {
      "ano": 2018,
      "entidade": "Prefeitura do Município de Londrina",
      "empenhado": 934899227.59,
      "liquidado": 846694025.21,
      "pago": 835427949.96
    },
    {
      "ano": 2018,
      "entidade": "Fundo Municipal de Saúde de Londrina",
      "empenhado": 665372171.1,
      "liquidado": 648755345.07,
      "pago": 636992107.98
    },
    {
      "ano": 2018,
      "entidade": "CAAPSML - Plano de Previdência Social - Fundo Previdenciário",
      "empenhado": 296567345.29,
      "liquidado": 295458570.21,
      "pago": 295460509.35
    },
    {
      "ano": 2018,
      "entidade": "Fundo de Urbanização de Londrina",
      "empenhado": 86212521.3,
      "liquidado": 80995246.97,
      "pago": 78520416.67
    },
    {
      "ano": 2018,
      "entidade": "Fundo de Assistência à Saúde dos Servidores Municipais de Londrina",
      "empenhado": 67883797.78,
      "liquidado": 56711601.34,
      "pago": 56068907.15
    }
  ]
}